<?xml version='1.0' encoding='UTF-8'?>
<song xmlns="http://openlyrics.info/namespace/2009/song" version="0.8" createdIn="OpenLP 2.4.6" modifiedIn="OpenLP 2.4.6" modifiedDate="2017-10-08T18:36:18">
  <properties>
    <titles>
      <title>390. Jer temessük el a testet</title>
    </titles>
    <copyright>Hé-390</copyright>
    <authors>
      <author>ismeretlen szerző</author>
    </authors>
  </properties>
  <lyrics>
    <verse name="i1">
      <lines>Jer temessük el a testet...<br/><br/>Hitünk énekei<br/>390. ének</lines>
    </verse>
    <verse name="v1">
      <lines>Jer temessük el a testet, melyről kétségünk nem lehet, hogy az ítéletnek napján fel fog támadni igazán!</lines>
    </verse>
    <verse name="v2">
      <lines>Porból való eredete, azért porrá kell lennie, de majd feltámad a sírból, mihelyt az Úrnak szava szól.</lines>
    </verse>
    <verse name="v3">
      <lines>Jer, hagyjuk itt őt aludni, Krisztus Jézusban nyugodni és mi szüntelen vigyázzunk, mert nékünk is meg kell halnunk.</lines>
    </verse>
    <verse name="v4">
      <lines>Úr Krisztusunk dicsértessék, örökké magasztaltassék egyetemben az Atyával és Szentlélek Úr Istennel!</lines>
    </verse>
  </lyrics>
</song>
