<?xml version='1.0' encoding='UTF-8'?>
<song xmlns="http://openlyrics.info/namespace/2009/song" version="0.8" createdIn="OpenLP 2.4.6" modifiedIn="OpenLP 2.4.6" modifiedDate="2017-10-01T14:12:41">
  <properties>
    <titles>
      <title>B147 E harcok dúlta földre szállt</title>
    </titles>
    <authors>
      <author>ismeretlen szerző</author>
    </authors>
  </properties>
  <lyrics>
    <verse name="i1">
      <lines>E harcok dúlta földre szállt<br/>B147</lines>
    </verse>
    <verse name="v1">
      <lines>E harcok dúlta földre szállt A béke nagy Királya; Elhagyta égi trónusát, Bús életünket szánva… A menny békéjét hozta le, És szeretettel volt tele Minden szívdobbanása.</lines>
    </verse>
    <verse name="v2">
      <lines>A háborúnak fellegét Elűzi békessége; A földdel frigyre lép az ég, És meghajol nevére. A népek s minden nemzetek, Ha benne egyet értenek, Úgy lesz e földön béke.</lines>
    </verse>
    <verse name="v3">
      <lines>A zord szívekben szózata Új életet varázsol; Megolvad kopja, kard vasa, Hol békessége lángol. Nem pusztít harag szelleme, De megújul mindenfele A föld az ő szavától.</lines>
    </verse>
    <verse name="v4">
      <lines>Ó, Krisztusunk, hadd járja át Békéd e széles földet, S hadd munkáljuk egymás javát, Amint tanultuk tőled! Hogy tündököljön végtelen’ Szent országlásod mindenen, Ó, adj hát békességet!</lines>
    </verse>
  </lyrics>
</song>
