<?xml version='1.0' encoding='UTF-8'?>
<song xmlns="http://openlyrics.info/namespace/2009/song" version="0.8" createdIn="OpenLP 2.4.6" modifiedIn="OpenLP 2.4.6" modifiedDate="2017-10-01T14:13:10">
  <properties>
    <titles>
      <title>B385 Ó, szívem jól vigyázz</title>
    </titles>
    <authors>
      <author>ismeretlen szerző</author>
    </authors>
  </properties>
  <lyrics>
    <verse name="i1">
      <lines>Ó, szívem jól vigyázz<br/>B385</lines>
    </verse>
    <verse name="v1">
      <lines>Ó, szívem jól vigyázz, Sok ellenség tör rád, Bűn gyümölcse csak kín és gyász, Jól küzdj ellene hát!</lines>
    </verse>
    <verse name="v2">
      <lines>Csak gyáva szolga fél: Te harcolj hitedért! Az győz, ki imádsággal él, S az útról le nem tér.</lines>
    </verse>
    <verse name="v3">
      <lines>Még győznöd kell neked, A küzdés tart tovább, De végül majd font átveszed Az Úrtól koronád.</lines>
    </verse>
    <verse name="v4">
      <lines>Légy sírig hűséges, És légy hitben erős, Erőért az Úrhoz siess, Fönt pálmát nyer, ki győz!</lines>
    </verse>
  </lyrics>
</song>
