<?xml version='1.0' encoding='UTF-8'?>
<song xmlns="http://openlyrics.info/namespace/2009/song" version="0.8" createdIn="OpenLP 2.4.6" modifiedIn="OpenLP 2.4.6" modifiedDate="2017-10-01T14:13:52">
  <properties>
    <titles>
      <title>Hozzád száll dalunk</title>
    </titles>
    <verseOrder>i1 v1 c1 v2 c1</verseOrder>
    <authors>
      <author>ismeretlen szerző</author>
    </authors>
  </properties>
  <lyrics>
    <verse name="i1">
      <lines>Hozzád száll dalunk</lines>
    </verse>
    <verse name="v1">
      <lines>Hozzád száll dalunk s hálaa szavunk, téged dicsérjen, Urunk! Életünk Tiéd, áldozatul, hozzád vezessen, az utunk.</lines>
    </verse>
    <verse name="c1">
      <lines>Jó Urunk, életünkkel szolgálunk. Te adtad örörkül tisztaságod, az életünkkel szolgálunk.</lines>
    </verse>
    <verse name="v2">
      <lines>Dalunk száll feléd, nagy örömmel, tisztán állunk már eléd. Az igaz imánk hozzád talál, hozzád tartozunk régen már.</lines>
    </verse>
  </lyrics>
</song>
