<?xml version='1.0' encoding='UTF-8'?>
<song xmlns="http://openlyrics.info/namespace/2009/song" version="0.8" createdIn="OpenLP 2.4.6" modifiedIn="OpenLP 2.4.6" modifiedDate="2017-10-01T14:14:07">
  <properties>
    <titles>
      <title>Jöjj el az élet vizéhez</title>
    </titles>
    <authors>
      <author>ismeretlen szerző</author>
    </authors>
  </properties>
  <lyrics>
    <verse name="i1">
      <lines>Jöjj el az élet vizéhez</lines>
    </verse>
    <verse name="v1">
      <lines>Jöjj el az élet vizéhez, nélküle szomjas a szív,<br/>Átok alól szabadulsz itt, hű Urad Ő, aki hív.</lines>
    </verse>
    <verse name="c1">
      <lines>Jöjj hát, siess, jöjj, vár reád: <br/>béke a földön, az üdv odaát!<br/>Itt van az élet, a forrás, nincs sehol és soha más.</lines>
    </verse>
    <verse name="v2">
      <lines>Jöjj megújulni e vízben, új lesz a hit, szeretet,<br/>eltűnik itt, ami régi, kezded az új életet.</lines>
    </verse>
    <verse name="v3">
      <lines>Jöjj hát az élet vizéhez, Jézus kínálja neked,<br/>Árad az élet belőled, kútfeje lesz a szíved.</lines>
    </verse>
  </lyrics>
</song>
