<?xml version='1.0' encoding='UTF-8'?>
<song xmlns="http://openlyrics.info/namespace/2009/song" version="0.8" createdIn="OpenLP 2.4.6" modifiedIn="OpenLP 2.4.6" modifiedDate="2017-10-01T14:13:01">
  <properties>
    <titles>
      <title>B316 Nem láthat bár e földi szem</title>
    </titles>
    <authors>
      <author>ismeretlen szerző</author>
    </authors>
  </properties>
  <lyrics>
    <verse name="i1">
      <lines>Nem láthat bár e földi szem<br/>B316</lines>
    </verse>
    <verse name="v1">
      <lines>Nem láthat bár e földi szem, Jézus tiéd vagyok, Bár arcod felhő rejti el, Mégis felém ragyog.</lines>
    </verse>
    <verse name="v2">
      <lines>Fülem nem hallja hangodat, Mégis beszélsz velem; S boldogságot csupán az ad, Ha szódat érthetem.</lines>
    </verse>
    <verse name="v3">
      <lines>Képed betölti lelkemet, Utam bármerre visz, Tudom, hogy szent kezed vezet, ha azt nem látom is.</lines>
    </verse>
    <verse name="v4">
      <lines>Elzengni, hogy mi vagy nekem, ó, nincsen arra szó; Most hitből áll csak életem, S mégis mindez való.</lines>
    </verse>
    <verse name="v5">
      <lines>De majd a felhő felszakad, Mely most még rejteget, És színről színre áldalak, Hogy nálad élhetek.</lines>
    </verse>
  </lyrics>
</song>
