<?xml version='1.0' encoding='UTF-8'?>
<song xmlns="http://openlyrics.info/namespace/2009/song" version="0.8" createdIn="OpenLP 2.4.6" modifiedIn="OpenLP 2.4.6" modifiedDate="2017-10-01T14:13:04">
  <properties>
    <titles>
      <title>B336 Száll az idő sebes szárnyon</title>
    </titles>
    <authors>
      <author>ismeretlen szerző</author>
    </authors>
  </properties>
  <lyrics>
    <verse name="i1">
      <lines>Száll az idő sebes szárnyon<br/>B336</lines>
    </verse>
    <verse name="v1">
      <lines>Száll az idő sebes szárnyon, Nincs megállás a világon, Napok, évek tűnnek el; Földünk minden népe újra, Reménységben megújulva, Újesztendőt ünnepel.</lines>
    </verse>
    <verse name="v2">
      <lines>Elmúlik az élet nyara, Elmúlik a télnek hava, Öröm, gond és fájdalom; Futó felhőt amint látunk, Úgy röppen el ifjúságunk, S testünk is csak sárhalom.</lines>
    </verse>
    <verse name="v3">
      <lines>Csak egy nem változik: Isten, Benne múlhatatlan minden, Dicsőség és szeretet. Csak ő tudja megmenteni, Öröklétbe behelyezni Az emberi lelkeket!</lines>
    </verse>
    <verse name="v4">
      <lines>Üdvözlégy hát, Újév reggel, Jöjj békével, szeretettel, Hozzál erős, szent hitet! Mi Atyánk, ki vagy a mennyben, Adjál ez új esztendőben Mindnyájunknak új szívet!</lines>
    </verse>
  </lyrics>
</song>
